{"Pump Out Program": {"Water_Level": "High", "Message": "Suspected clogging! Please check Drain Pump for possible defect or necessary maintenance!", "Exit_Water_Flow": "No Flow", "Time": "06/07/21 14:00:23"}, "Door Lock Program": {"Lock": "Locked", "Message": "Pressure Sensor, Door Lock Sensor and Door Lock are working properly.", "Pressure": "Normal", "Time": "06/07/21 14:00:31"}, "Fan Program": {"Vibration": "Normal", "Message": "Please check Blower for defect or necessary maintenance!", "Loudness": "High", "Mass_Air_Flow": "Normal", "Time": "06/07/21 14:00:24"}, "Drum Motor Program": {"Loudness": "High", "Rotation_Speed": "High", "Vibration": "Normal", "Message": "Drum Motor is too fast and causes loudness. Please check for repair.", "Time": "06/07/21 14:00:27"}, "Water Inlet Program": {"Water_Level": "Normal", "Message": "Water Flow Sensor, Water Fill Level Sensor and Water Inlet Valve are working properly.", "Entrance_Water_Flow": "Flow OK", "Water_Hardness": "Normal", "Time": "06/07/21 14:00:33"}, "Long Time Check": {"Temperature": "Normal", "Washing_Powder_Fill_Level": "Normal", "Laundry_Weight": "High", "Laundry_Fill_Level": "High", "Washing_Powder": "Weak", "Usage_Frequency": "Low", "Used_Modes": "Normal", "Water_Hardness": "Hard", "Message": "Consider reducing the amount of laundry.| Laundry is overweight, please reduce laundry weight to preserve system lifetime.| Consider buying a stronger washing powder or adding more detergent.| Washing machine is seldom used.| The most frequently used mode is Normal mode. Temperature is correctly measured.", "Time": "06/07/21 14:00:04"}}